desim/__init__.py
desim/data.py
desim/interface.py
desim/simulation.py
desim_tool-0.3.3.dist-info/LICENSE.md
desim_tool-0.3.3.dist-info/METADATA
desim_tool-0.3.3.dist-info/WHEEL
desim_tool-0.3.3.dist-info/top_level.txt
desim_tool-0.3.3.dist-info/RECORD
