Metadata-Version: 2.1
Name: desim-tool
Version: 0.3.3
Summary: A discrete event simulator
Home-page: https://github.com/sed-group/desim
Author: Erik
Author-email: erik.00.berg@gmail.com
License-File: LICENSE.md
Requires-Dist: simpy
Requires-Dist: numpy
